code_generation/__init__.py
code_generation/code_generator.py
code_generation/code_style.py
code_generation/cpp_array.py
code_generation/cpp_class.py
code_generation/cpp_enum.py
code_generation/cpp_function.py
code_generation/cpp_generator.py
code_generation/cpp_variable.py
code_generation/html_generator.py
code_generation/version.py
code_generation-2.3.0.dist-info/LICENSE
code_generation-2.3.0.dist-info/METADATA
code_generation-2.3.0.dist-info/WHEEL
code_generation-2.3.0.dist-info/top_level.txt
code_generation-2.3.0.dist-info/RECORD
