Metadata-Version: 2.1
Name: code-generation
Version: 2.3.0
Summary: Provides functionality of generating source code programmatically
Home-page: https://github.com/yuchdev/code_generator
Author: Yurii Cherkasov
Author-email: strategarius@protonmail.com
Project-URL: Bug Tracker, https://github.com/yuchdev/code_generator/issues
Classifier: Development Status :: 5 - Production/Stable
Classifier: Intended Audience :: Developers
Classifier: Programming Language :: Python :: 3
Classifier: License :: OSI Approved :: MIT License
Classifier: Operating System :: OS Independent
Requires-Python: >=3.8
License-File: LICENSE
Requires-Dist: pathlib
